{
  "dataset": "Explainability dataset",
  "image": {
    "width": 1640,
    "height": 1078,
    "original_filename": "labeller5_043127HB.jpg",
    "filename": "labeller5_043127HB.jpg",
    "url": "https://darwin.v7labs.com/api/images/90127180/original",
    "thumbnail_url": "https://darwin.v7labs.com/api/images/90127180/thumbnail",
    "path": "/",
    "workview_url": "https://darwin.v7labs.com/workview?dataset=220222&image=6572"
  },
  "annotations": [
    {
      "attributes": [
        "White",
        "Fine"
      ],
      "bounding_box": {
        "h": 168.55,
        "w": 732.4800000000001,
        "x": 368.9,
        "y": 325.32
      },
      "complex_polygon": {
        "path": [
          [
            {
              "x": 419.46,
              "y": 447.83
            },
            {
              "x": 417.68,
              "y": 445.59
            },
            {
              "x": 417.68,
              "y": 450.06
            }
          ],
          [
            {
              "x": 627.29,
              "y": 432.06
            },
            {
              "x": 627.29,
              "y": 399.97
            },
            {
              "x": 625.19,
              "y": 390.78
            },
            {
              "x": 623.05,
              "y": 386.5
            },
            {
              "x": 612.89,
              "y": 372.72
            },
            {
              "x": 610.74,
              "y": 371.64
            },
            {
              "x": 604.34,
              "y": 364.16
            },
            {
              "x": 600.16,
              "y": 362.15
            },
            {
              "x": 597.92,
              "y": 359.88
            },
            {
              "x": 577.19,
              "y": 350.47
            },
            {
              "x": 578.1,
              "y": 346.5
            },
            {
              "x": 576.0,
              "y": 337.31
            },
            {
              "x": 570.12,
              "y": 329.94
            },
            {
              "x": 561.63,
              "y": 325.85
            },
            {
              "x": 550.5,
              "y": 325.85
            },
            {
              "x": 550.5,
              "y": 325.32
            },
            {
              "x": 513.71,
              "y": 325.85
            },
            {
              "x": 505.22,
              "y": 329.94
            },
            {
              "x": 500.94,
              "y": 334.22
            },
            {
              "x": 494.82,
              "y": 342.63
            },
            {
              "x": 487.95,
              "y": 349.34
            },
            {
              "x": 480.08,
              "y": 353.21
            },
            {
              "x": 468.79,
              "y": 353.66
            },
            {
              "x": 449.54,
              "y": 360.07
            },
            {
              "x": 445.26,
              "y": 360.07
            },
            {
              "x": 438.85,
              "y": 362.21
            },
            {
              "x": 430.36,
              "y": 366.3
            },
            {
              "x": 424.22,
              "y": 372.91
            },
            {
              "x": 420.03,
              "y": 372.91
            },
            {
              "x": 420.03,
              "y": 372.38
            },
            {
              "x": 389.65,
              "y": 372.91
            },
            {
              "x": 381.16,
              "y": 377.0
            },
            {
              "x": 379.02,
              "y": 379.13
            },
            {
              "x": 373.14,
              "y": 386.5
            },
            {
              "x": 371.0,
              "y": 392.92
            },
            {
              "x": 368.9,
              "y": 402.11
            },
            {
              "x": 368.9,
              "y": 417.08
            },
            {
              "x": 375.32,
              "y": 443.43
            },
            {
              "x": 375.32,
              "y": 462.0
            },
            {
              "x": 377.42,
              "y": 471.19
            },
            {
              "x": 381.36,
              "y": 476.13
            },
            {
              "x": 383.84,
              "y": 481.88
            },
            {
              "x": 389.72,
              "y": 489.25
            },
            {
              "x": 398.21,
              "y": 493.34
            },
            {
              "x": 402.92,
              "y": 493.34
            },
            {
              "x": 402.92,
              "y": 493.87
            },
            {
              "x": 431.15,
              "y": 493.34
            },
            {
              "x": 443.92,
              "y": 487.12
            },
            {
              "x": 460.33,
              "y": 466.07
            },
            {
              "x": 512.0,
              "y": 466.07
            },
            {
              "x": 512.0,
              "y": 465.54
            },
            {
              "x": 516.71,
              "y": 465.54
            },
            {
              "x": 527.96,
              "y": 461.79
            },
            {
              "x": 546.65,
              "y": 461.26
            },
            {
              "x": 557.9,
              "y": 457.51
            },
            {
              "x": 597.99,
              "y": 456.98
            },
            {
              "x": 606.54,
              "y": 454.84
            },
            {
              "x": 619.31,
              "y": 448.62
            },
            {
              "x": 625.19,
              "y": 441.25
            }
          ],
          [
            {
              "x": 1101.38,
              "y": 425.86
            },
            {
              "x": 1099.28,
              "y": 416.67
            },
            {
              "x": 1093.4,
              "y": 409.3
            },
            {
              "x": 1084.91,
              "y": 405.21
            },
            {
              "x": 1078.02,
              "y": 404.68
            },
            {
              "x": 1078.02,
              "y": 405.21
            },
            {
              "x": 1072.14,
              "y": 405.77
            },
            {
              "x": 1042.95,
              "y": 405.77
            },
            {
              "x": 1039.24,
              "y": 405.21
            },
            {
              "x": 1034.71,
              "y": 403.02
            },
            {
              "x": 1027.08,
              "y": 401.93
            },
            {
              "x": 1015.07,
              "y": 398.66
            },
            {
              "x": 980.4,
              "y": 393.2
            },
            {
              "x": 973.6,
              "y": 389.93
            },
            {
              "x": 959.66,
              "y": 389.4
            },
            {
              "x": 953.96,
              "y": 386.66
            },
            {
              "x": 925.59,
              "y": 384.47
            },
            {
              "x": 909.22,
              "y": 380.11
            },
            {
              "x": 894.69,
              "y": 379.02
            },
            {
              "x": 894.69,
              "y": 378.49
            },
            {
              "x": 871.12,
              "y": 378.49
            },
            {
              "x": 866.66,
              "y": 376.83
            },
            {
              "x": 861.95,
              "y": 376.83
            },
            {
              "x": 861.95,
              "y": 376.31
            },
            {
              "x": 773.56,
              "y": 376.31
            },
            {
              "x": 773.56,
              "y": 376.83
            },
            {
              "x": 768.85,
              "y": 376.83
            },
            {
              "x": 765.57,
              "y": 377.93
            },
            {
              "x": 761.21,
              "y": 377.93
            },
            {
              "x": 752.72,
              "y": 382.02
            },
            {
              "x": 747.8,
              "y": 385.56
            },
            {
              "x": 743.75,
              "y": 386.66
            },
            {
              "x": 730.89,
              "y": 392.93
            },
            {
              "x": 727.62,
              "y": 396.2
            },
            {
              "x": 720.65,
              "y": 405.75
            },
            {
              "x": 716.36,
              "y": 428.04
            },
            {
              "x": 716.36,
              "y": 444.41
            },
            {
              "x": 718.46,
              "y": 453.6
            },
            {
              "x": 722.57,
              "y": 460.1
            },
            {
              "x": 723.92,
              "y": 464.51
            },
            {
              "x": 729.8,
              "y": 471.88
            },
            {
              "x": 734.01,
              "y": 473.91
            },
            {
              "x": 736.35,
              "y": 476.25
            },
            {
              "x": 747.02,
              "y": 481.43
            },
            {
              "x": 758.86,
              "y": 482.52
            },
            {
              "x": 763.39,
              "y": 484.7
            },
            {
              "x": 778.67,
              "y": 485.79
            },
            {
              "x": 783.03,
              "y": 486.88
            },
            {
              "x": 787.74,
              "y": 486.88
            },
            {
              "x": 787.74,
              "y": 487.41
            },
            {
              "x": 809.57,
              "y": 487.41
            },
            {
              "x": 809.57,
              "y": 486.88
            },
            {
              "x": 814.28,
              "y": 486.88
            },
            {
              "x": 828.46,
              "y": 483.61
            },
            {
              "x": 836.95,
              "y": 479.52
            },
            {
              "x": 840.04,
              "y": 477.2
            },
            {
              "x": 845.92,
              "y": 474.88
            },
            {
              "x": 855.75,
              "y": 472.7
            },
            {
              "x": 864.24,
              "y": 468.61
            },
            {
              "x": 867.51,
              "y": 465.33
            },
            {
              "x": 876.24,
              "y": 460.97
            },
            {
              "x": 877.81,
              "y": 459.0
            },
            {
              "x": 896.97,
              "y": 448.96
            },
            {
              "x": 900.79,
              "y": 444.82
            },
            {
              "x": 905.07,
              "y": 460.15
            },
            {
              "x": 907.08,
              "y": 462.67
            },
            {
              "x": 909.44,
              "y": 469.97
            },
            {
              "x": 915.32,
              "y": 477.34
            },
            {
              "x": 922.95,
              "y": 484.98
            },
            {
              "x": 934.72,
              "y": 490.16
            },
            {
              "x": 939.43,
              "y": 490.16
            },
            {
              "x": 939.43,
              "y": 490.69
            },
            {
              "x": 969.24,
              "y": 490.16
            },
            {
              "x": 983.42,
              "y": 484.7
            },
            {
              "x": 993.25,
              "y": 483.61
            },
            {
              "x": 996.68,
              "y": 481.96
            },
            {
              "x": 1043.44,
              "y": 481.43
            },
            {
              "x": 1050.12,
              "y": 479.22
            },
            {
              "x": 1060.9,
              "y": 477.06
            },
            {
              "x": 1074.85,
              "y": 469.7
            },
            {
              "x": 1090.55,
              "y": 450.32
            },
            {
              "x": 1092.23,
              "y": 442.98
            },
            {
              "x": 1093.4,
              "y": 442.42
            },
            {
              "x": 1099.28,
              "y": 435.05
            }
          ]
        ]
      },
      "name": "Scale"
    },
    {
      "attributes": [
        "Thin",
        "Poorly-circumscribed",
        "Red"
      ],
      "bounding_box": {
        "h": 286.79999999999995,
        "w": 833.53,
        "x": 358.43,
        "y": 242.08
      },
      "complex_polygon": {
        "path": [
          [
            {
              "x": 675.79,
              "y": 389.85
            },
            {
              "x": 675.79,
              "y": 351.65
            },
            {
              "x": 672.6,
              "y": 338.1
            },
            {
              "x": 663.87,
              "y": 325.0
            },
            {
              "x": 657.99,
              "y": 317.63
            },
            {
              "x": 650.35,
              "y": 311.08
            },
            {
              "x": 640.9,
              "y": 306.37
            },
            {
              "x": 639.43,
              "y": 304.54
            },
            {
              "x": 626.99,
              "y": 298.42
            },
            {
              "x": 623.07,
              "y": 294.71
            },
            {
              "x": 615.43,
              "y": 290.35
            },
            {
              "x": 601.48,
              "y": 284.08
            },
            {
              "x": 594.93,
              "y": 282.98
            },
            {
              "x": 589.48,
              "y": 280.8
            },
            {
              "x": 585.11,
              "y": 280.8
            },
            {
              "x": 581.84,
              "y": 279.71
            },
            {
              "x": 558.69,
              "y": 279.18
            },
            {
              "x": 554.56,
              "y": 277.53
            },
            {
              "x": 531.95,
              "y": 274.25
            },
            {
              "x": 507.63,
              "y": 261.16
            },
            {
              "x": 490.6,
              "y": 256.36
            },
            {
              "x": 484.71,
              "y": 253.52
            },
            {
              "x": 472.71,
              "y": 251.34
            },
            {
              "x": 461.8,
              "y": 248.06
            },
            {
              "x": 448.7,
              "y": 246.97
            },
            {
              "x": 425.79,
              "y": 242.61
            },
            {
              "x": 421.08,
              "y": 242.61
            },
            {
              "x": 421.08,
              "y": 242.08
            },
            {
              "x": 400.0,
              "y": 242.61
            },
            {
              "x": 397.73,
              "y": 243.7
            },
            {
              "x": 394.54,
              "y": 243.7
            },
            {
              "x": 386.05,
              "y": 247.79
            },
            {
              "x": 378.41,
              "y": 252.15
            },
            {
              "x": 369.68,
              "y": 260.88
            },
            {
              "x": 363.8,
              "y": 268.25
            },
            {
              "x": 360.53,
              "y": 275.89
            },
            {
              "x": 358.43,
              "y": 285.08
            },
            {
              "x": 358.43,
              "y": 373.48
            },
            {
              "x": 359.52,
              "y": 381.12
            },
            {
              "x": 365.98,
              "y": 405.58
            },
            {
              "x": 367.82,
              "y": 408.04
            },
            {
              "x": 370.43,
              "y": 419.87
            },
            {
              "x": 371.52,
              "y": 433.5
            },
            {
              "x": 376.98,
              "y": 457.92
            },
            {
              "x": 376.98,
              "y": 464.05
            },
            {
              "x": 378.07,
              "y": 470.6
            },
            {
              "x": 381.26,
              "y": 484.15
            },
            {
              "x": 383.53,
              "y": 486.99
            },
            {
              "x": 383.53,
              "y": 503.34
            },
            {
              "x": 385.63,
              "y": 512.53
            },
            {
              "x": 386.72,
              "y": 515.8
            },
            {
              "x": 393.69,
              "y": 524.26
            },
            {
              "x": 402.18,
              "y": 528.35
            },
            {
              "x": 406.89,
              "y": 528.35
            },
            {
              "x": 406.89,
              "y": 528.88
            },
            {
              "x": 420.33,
              "y": 528.35
            },
            {
              "x": 436.7,
              "y": 523.99
            },
            {
              "x": 465.07,
              "y": 511.98
            },
            {
              "x": 504.36,
              "y": 506.53
            },
            {
              "x": 520.73,
              "y": 503.25
            },
            {
              "x": 538.19,
              "y": 496.71
            },
            {
              "x": 560.86,
              "y": 484.98
            },
            {
              "x": 569.67,
              "y": 478.35
            },
            {
              "x": 581.6,
              "y": 471.88
            },
            {
              "x": 605.6,
              "y": 456.6
            },
            {
              "x": 612.15,
              "y": 450.06
            },
            {
              "x": 617.61,
              "y": 446.78
            },
            {
              "x": 627.42,
              "y": 434.05
            },
            {
              "x": 629.61,
              "y": 432.6
            },
            {
              "x": 642.04,
              "y": 417.59
            },
            {
              "x": 647.22,
              "y": 409.2
            },
            {
              "x": 649.9,
              "y": 410.5
            },
            {
              "x": 659.32,
              "y": 410.5
            },
            {
              "x": 667.81,
              "y": 406.41
            },
            {
              "x": 673.69,
              "y": 399.04
            }
          ],
          [
            {
              "x": 917.28,
              "y": 424.94
            },
            {
              "x": 917.58,
              "y": 424.56
            },
            {
              "x": 917.67,
              "y": 424.83
            },
            {
              "x": 917.75,
              "y": 425.16
            }
          ],
          [
            {
              "x": 1191.96,
              "y": 480.42
            },
            {
              "x": 1191.96,
              "y": 454.23
            },
            {
              "x": 1188.68,
              "y": 434.59
            },
            {
              "x": 1186.58,
              "y": 425.4
            },
            {
              "x": 1181.13,
              "y": 415.58
            },
            {
              "x": 1180.04,
              "y": 411.21
            },
            {
              "x": 1174.69,
              "y": 400.12
            },
            {
              "x": 1174.5,
              "y": 388.75
            },
            {
              "x": 1173.41,
              "y": 381.11
            },
            {
              "x": 1173.41,
              "y": 328.73
            },
            {
              "x": 1169.12,
              "y": 311.91
            },
            {
              "x": 1160.39,
              "y": 297.72
            },
            {
              "x": 1157.12,
              "y": 291.17
            },
            {
              "x": 1156.03,
              "y": 286.81
            },
            {
              "x": 1153.11,
              "y": 283.14
            },
            {
              "x": 1151.66,
              "y": 279.17
            },
            {
              "x": 1145.78,
              "y": 271.8
            },
            {
              "x": 1132.69,
              "y": 263.07
            },
            {
              "x": 1124.2,
              "y": 258.98
            },
            {
              "x": 1119.49,
              "y": 258.98
            },
            {
              "x": 1119.49,
              "y": 258.45
            },
            {
              "x": 1091.86,
              "y": 258.98
            },
            {
              "x": 1083.37,
              "y": 263.07
            },
            {
              "x": 1079.01,
              "y": 266.34
            },
            {
              "x": 1063.73,
              "y": 281.62
            },
            {
              "x": 1055.67,
              "y": 292.26
            },
            {
              "x": 1052.39,
              "y": 298.81
            },
            {
              "x": 1050.56,
              "y": 306.85
            },
            {
              "x": 1045.84,
              "y": 314.09
            },
            {
              "x": 1043.84,
              "y": 320.11
            },
            {
              "x": 1030.64,
              "y": 335.26
            },
            {
              "x": 1019.24,
              "y": 339.2
            },
            {
              "x": 981.04,
              "y": 339.2
            },
            {
              "x": 970.74,
              "y": 336.83
            },
            {
              "x": 966.04,
              "y": 332.14
            },
            {
              "x": 960.69,
              "y": 323.91
            },
            {
              "x": 950.45,
              "y": 312.17
            },
            {
              "x": 944.99,
              "y": 307.81
            },
            {
              "x": 936.5,
              "y": 303.72
            },
            {
              "x": 927.93,
              "y": 301.54
            },
            {
              "x": 923.4,
              "y": 299.35
            },
            {
              "x": 901.12,
              "y": 298.82
            },
            {
              "x": 896.97,
              "y": 293.62
            },
            {
              "x": 888.48,
              "y": 289.53
            },
            {
              "x": 881.59,
              "y": 289.53
            },
            {
              "x": 881.59,
              "y": 289.0
            },
            {
              "x": 871.42,
              "y": 289.53
            },
            {
              "x": 862.93,
              "y": 293.62
            },
            {
              "x": 858.57,
              "y": 297.99
            },
            {
              "x": 855.06,
              "y": 298.26
            },
            {
              "x": 846.57,
              "y": 302.35
            },
            {
              "x": 840.96,
              "y": 307.96
            },
            {
              "x": 826.92,
              "y": 315.45
            },
            {
              "x": 823.57,
              "y": 318.8
            },
            {
              "x": 818.19,
              "y": 322.0
            },
            {
              "x": 811.25,
              "y": 329.86
            },
            {
              "x": 805.1,
              "y": 334.0
            },
            {
              "x": 794.18,
              "y": 347.09
            },
            {
              "x": 781.09,
              "y": 355.82
            },
            {
              "x": 775.19,
              "y": 363.3
            },
            {
              "x": 756.74,
              "y": 376.83
            },
            {
              "x": 747.26,
              "y": 380.92
            },
            {
              "x": 742.9,
              "y": 384.2
            },
            {
              "x": 721.74,
              "y": 410.12
            },
            {
              "x": 719.57,
              "y": 419.19
            },
            {
              "x": 717.37,
              "y": 422.12
            },
            {
              "x": 715.27,
              "y": 431.31
            },
            {
              "x": 715.27,
              "y": 453.14
            },
            {
              "x": 717.37,
              "y": 462.33
            },
            {
              "x": 720.8,
              "y": 468.26
            },
            {
              "x": 721.74,
              "y": 472.15
            },
            {
              "x": 723.4,
              "y": 474.23
            },
            {
              "x": 725.01,
              "y": 478.7
            },
            {
              "x": 730.89,
              "y": 486.07
            },
            {
              "x": 735.26,
              "y": 489.34
            },
            {
              "x": 743.75,
              "y": 493.43
            },
            {
              "x": 748.11,
              "y": 494.52
            },
            {
              "x": 795.38,
              "y": 495.05
            },
            {
              "x": 795.38,
              "y": 494.52
            },
            {
              "x": 810.66,
              "y": 493.96
            },
            {
              "x": 810.66,
              "y": 493.43
            },
            {
              "x": 821.92,
              "y": 492.34
            },
            {
              "x": 844.09,
              "y": 481.68
            },
            {
              "x": 851.38,
              "y": 479.25
            },
            {
              "x": 859.87,
              "y": 475.16
            },
            {
              "x": 868.75,
              "y": 467.36
            },
            {
              "x": 871.27,
              "y": 466.15
            },
            {
              "x": 882.01,
              "y": 462.31
            },
            {
              "x": 891.82,
              "y": 461.22
            },
            {
              "x": 895.1,
              "y": 461.22
            },
            {
              "x": 899.31,
              "y": 462.43
            },
            {
              "x": 904.68,
              "y": 465.39
            },
            {
              "x": 909.86,
              "y": 471.88
            },
            {
              "x": 912.04,
              "y": 472.97
            },
            {
              "x": 917.5,
              "y": 479.52
            },
            {
              "x": 919.68,
              "y": 480.61
            },
            {
              "x": 922.95,
              "y": 483.89
            },
            {
              "x": 931.44,
              "y": 487.98
            },
            {
              "x": 939.08,
              "y": 490.16
            },
            {
              "x": 1018.0,
              "y": 490.69
            },
            {
              "x": 1018.0,
              "y": 490.16
            },
            {
              "x": 1030.0,
              "y": 489.6
            },
            {
              "x": 1030.0,
              "y": 489.07
            },
            {
              "x": 1051.08,
              "y": 486.88
            },
            {
              "x": 1055.22,
              "y": 485.23
            },
            {
              "x": 1085.78,
              "y": 485.23
            },
            {
              "x": 1088.16,
              "y": 485.71
            },
            {
              "x": 1112.6,
              "y": 496.71
            },
            {
              "x": 1116.96,
              "y": 496.71
            },
            {
              "x": 1146.42,
              "y": 505.44
            },
            {
              "x": 1156.25,
              "y": 509.8
            },
            {
              "x": 1160.96,
              "y": 509.8
            },
            {
              "x": 1160.96,
              "y": 510.33
            },
            {
              "x": 1174.4,
              "y": 509.8
            },
            {
              "x": 1182.89,
              "y": 505.71
            },
            {
              "x": 1188.77,
              "y": 498.34
            },
            {
              "x": 1190.87,
              "y": 488.06
            }
          ]
        ]
      },
      "name": "Plaque"
    },
    {
      "name": "Seborrheic dermatitis",
      "tag": {}
    },
    {
      "name": "Male",
      "tag": {}
    },
    {
      "name": "Symmetrical",
      "tag": {}
    }
  ]
}