{
  "dataset": "Explainability dataset",
  "image": {
    "width": 1640,
    "height": 1078,
    "original_filename": "labeller2_043256HB.jpg",
    "filename": "labeller2_043256HB.jpg",
    "url": "https://darwin.v7labs.com/api/images/72772471/original",
    "thumbnail_url": "https://darwin.v7labs.com/api/images/72772471/thumbnail",
    "path": "/",
    "workview_url": "https://darwin.v7labs.com/workview?dataset=220222&image=3726"
  },
  "annotations": [
    {
      "attributes": [
        "Well-circumscribed",
        "Red"
      ],
      "bounding_box": {
        "h": 821.87,
        "w": 454.8599999999999,
        "x": 663.49,
        "y": 139.59
      },
      "complex_polygon": {
        "path": [
          [
            {
              "x": 954.34,
              "y": 366.88
            },
            {
              "x": 954.34,
              "y": 366.81
            },
            {
              "x": 954.35,
              "y": 366.87
            }
          ],
          [
            {
              "x": 1063.39,
              "y": 898.92
            },
            {
              "x": 1063.39,
              "y": 838.64
            },
            {
              "x": 1058.27,
              "y": 805.5
            },
            {
              "x": 1039.77,
              "y": 774.63
            },
            {
              "x": 1023.5,
              "y": 761.49
            },
            {
              "x": 1022.61,
              "y": 759.93
            },
            {
              "x": 1022.61,
              "y": 734.03
            },
            {
              "x": 1019.26,
              "y": 715.07
            },
            {
              "x": 1007.86,
              "y": 694.85
            },
            {
              "x": 997.22,
              "y": 684.21
            },
            {
              "x": 982.47,
              "y": 671.83
            },
            {
              "x": 964.38,
              "y": 665.25
            },
            {
              "x": 954.75,
              "y": 665.25
            },
            {
              "x": 954.75,
              "y": 664.4
            },
            {
              "x": 938.35,
              "y": 665.25
            },
            {
              "x": 929.85,
              "y": 650.52
            },
            {
              "x": 915.1,
              "y": 638.14
            },
            {
              "x": 897.0,
              "y": 631.56
            },
            {
              "x": 881.05,
              "y": 629.79
            },
            {
              "x": 871.42,
              "y": 629.79
            },
            {
              "x": 871.42,
              "y": 628.94
            },
            {
              "x": 853.69,
              "y": 628.94
            },
            {
              "x": 853.69,
              "y": 629.79
            },
            {
              "x": 844.06,
              "y": 629.79
            },
            {
              "x": 828.1,
              "y": 633.33
            },
            {
              "x": 804.69,
              "y": 641.69
            },
            {
              "x": 801.38,
              "y": 643.67
            },
            {
              "x": 793.35,
              "y": 630.61
            },
            {
              "x": 790.34,
              "y": 618.32
            },
            {
              "x": 790.34,
              "y": 347.51
            },
            {
              "x": 786.99,
              "y": 328.55
            },
            {
              "x": 777.36,
              "y": 311.87
            },
            {
              "x": 762.61,
              "y": 299.49
            },
            {
              "x": 744.52,
              "y": 292.91
            },
            {
              "x": 725.26,
              "y": 292.91
            },
            {
              "x": 707.17,
              "y": 299.49
            },
            {
              "x": 692.42,
              "y": 311.87
            },
            {
              "x": 682.79,
              "y": 328.55
            },
            {
              "x": 679.44,
              "y": 347.51
            },
            {
              "x": 679.44,
              "y": 620.56
            },
            {
              "x": 688.11,
              "y": 666.11
            },
            {
              "x": 693.43,
              "y": 678.53
            },
            {
              "x": 702.46,
              "y": 694.16
            },
            {
              "x": 704.07,
              "y": 699.8
            },
            {
              "x": 715.86,
              "y": 720.09
            },
            {
              "x": 694.76,
              "y": 728.57
            },
            {
              "x": 676.47,
              "y": 744.49
            },
            {
              "x": 666.84,
              "y": 761.17
            },
            {
              "x": 663.49,
              "y": 780.13
            },
            {
              "x": 663.49,
              "y": 790.77
            },
            {
              "x": 670.38,
              "y": 829.23
            },
            {
              "x": 680.01,
              "y": 845.91
            },
            {
              "x": 694.2,
              "y": 863.64
            },
            {
              "x": 699.52,
              "y": 872.51
            },
            {
              "x": 706.61,
              "y": 879.6
            },
            {
              "x": 735.54,
              "y": 904.39
            },
            {
              "x": 753.63,
              "y": 910.97
            },
            {
              "x": 760.73,
              "y": 912.74
            },
            {
              "x": 770.36,
              "y": 912.74
            },
            {
              "x": 770.36,
              "y": 913.59
            },
            {
              "x": 788.09,
              "y": 913.59
            },
            {
              "x": 788.09,
              "y": 912.74
            },
            {
              "x": 797.72,
              "y": 912.74
            },
            {
              "x": 815.81,
              "y": 906.16
            },
            {
              "x": 824.67,
              "y": 900.85
            },
            {
              "x": 839.42,
              "y": 888.47
            },
            {
              "x": 849.05,
              "y": 871.79
            },
            {
              "x": 850.82,
              "y": 866.47
            },
            {
              "x": 856.14,
              "y": 855.83
            },
            {
              "x": 859.25,
              "y": 838.26
            },
            {
              "x": 867.09,
              "y": 846.46
            },
            {
              "x": 870.74,
              "y": 864.69
            },
            {
              "x": 883.15,
              "y": 891.29
            },
            {
              "x": 892.38,
              "y": 907.29
            },
            {
              "x": 897.33,
              "y": 923.2
            },
            {
              "x": 906.96,
              "y": 939.88
            },
            {
              "x": 921.71,
              "y": 952.26
            },
            {
              "x": 939.8,
              "y": 958.84
            },
            {
              "x": 943.35,
              "y": 958.84
            },
            {
              "x": 952.21,
              "y": 960.62
            },
            {
              "x": 961.84,
              "y": 960.62
            },
            {
              "x": 961.84,
              "y": 961.46
            },
            {
              "x": 972.48,
              "y": 961.46
            },
            {
              "x": 972.48,
              "y": 960.62
            },
            {
              "x": 982.11,
              "y": 960.62
            },
            {
              "x": 998.07,
              "y": 958.84
            },
            {
              "x": 1012.69,
              "y": 953.52
            },
            {
              "x": 1017.57,
              "y": 953.52
            },
            {
              "x": 1035.66,
              "y": 946.94
            },
            {
              "x": 1050.41,
              "y": 934.56
            },
            {
              "x": 1060.04,
              "y": 917.88
            }
          ],
          [
            {
              "x": 1115.0,
              "y": 495.9
            },
            {
              "x": 1111.46,
              "y": 510.09
            },
            {
              "x": 1101.83,
              "y": 526.77
            },
            {
              "x": 1091.19,
              "y": 537.41
            },
            {
              "x": 1076.44,
              "y": 549.79
            },
            {
              "x": 1039.21,
              "y": 574.61
            },
            {
              "x": 1023.25,
              "y": 581.7
            },
            {
              "x": 1005.16,
              "y": 588.28
            },
            {
              "x": 976.79,
              "y": 591.83
            },
            {
              "x": 967.16,
              "y": 591.83
            },
            {
              "x": 967.16,
              "y": 592.67
            },
            {
              "x": 910.42,
              "y": 592.67
            },
            {
              "x": 910.42,
              "y": 591.83
            },
            {
              "x": 900.26,
              "y": 591.69
            },
            {
              "x": 891.69,
              "y": 593.6
            },
            {
              "x": 882.06,
              "y": 593.6
            },
            {
              "x": 882.06,
              "y": 594.45
            },
            {
              "x": 874.96,
              "y": 594.45
            },
            {
              "x": 874.96,
              "y": 593.6
            },
            {
              "x": 858.24,
              "y": 593.6
            },
            {
              "x": 840.15,
              "y": 587.02
            },
            {
              "x": 825.4,
              "y": 574.64
            },
            {
              "x": 815.77,
              "y": 557.96
            },
            {
              "x": 812.42,
              "y": 539.0
            },
            {
              "x": 815.77,
              "y": 520.04
            },
            {
              "x": 833.98,
              "y": 489.67
            },
            {
              "x": 840.94,
              "y": 460.68
            },
            {
              "x": 844.34,
              "y": 333.3
            },
            {
              "x": 844.34,
              "y": 303.19
            },
            {
              "x": 846.11,
              "y": 262.38
            },
            {
              "x": 846.11,
              "y": 234.04
            },
            {
              "x": 853.01,
              "y": 199.12
            },
            {
              "x": 856.55,
              "y": 190.26
            },
            {
              "x": 866.18,
              "y": 173.58
            },
            {
              "x": 871.5,
              "y": 166.49
            },
            {
              "x": 886.25,
              "y": 154.11
            },
            {
              "x": 896.37,
              "y": 150.42
            },
            {
              "x": 900.43,
              "y": 147.01
            },
            {
              "x": 918.52,
              "y": 140.43
            },
            {
              "x": 928.15,
              "y": 140.43
            },
            {
              "x": 928.15,
              "y": 139.59
            },
            {
              "x": 931.7,
              "y": 139.59
            },
            {
              "x": 931.7,
              "y": 140.43
            },
            {
              "x": 941.33,
              "y": 140.43
            },
            {
              "x": 959.42,
              "y": 147.01
            },
            {
              "x": 974.17,
              "y": 159.39
            },
            {
              "x": 983.04,
              "y": 168.26
            },
            {
              "x": 1009.63,
              "y": 200.17
            },
            {
              "x": 1019.26,
              "y": 216.85
            },
            {
              "x": 1033.45,
              "y": 245.22
            },
            {
              "x": 1060.04,
              "y": 325.01
            },
            {
              "x": 1063.39,
              "y": 343.97
            },
            {
              "x": 1066.87,
              "y": 386.84
            },
            {
              "x": 1078.84,
              "y": 398.81
            },
            {
              "x": 1100.06,
              "y": 416.48
            },
            {
              "x": 1109.69,
              "y": 433.16
            },
            {
              "x": 1115.0,
              "y": 445.57
            },
            {
              "x": 1118.35,
              "y": 464.53
            },
            {
              "x": 1118.35,
              "y": 476.94
            }
          ]
        ]
      },
      "name": "Patch"
    },
    {
      "name": "Seborrheic dermatitis",
      "tag": {}
    },
    {
      "name": "Seborrheic region",
      "tag": {}
    }
  ]
}